hermespy-1.5.0.dist-info/METADATA
hermespy-1.5.0.dist-info/WHEEL
hermespy-1.5.0.dist-info/RECORD
hermespy-1.5.0.dist-info/licenses/LICENSE
lib64/libaffect.so
hermespy/beamforming/conventional.py
hermespy/beamforming/nullsteeringbeamformer.py
hermespy/beamforming/operators.py
hermespy/beamforming/capon.py
hermespy/beamforming/beamformer.py
hermespy/beamforming/__init__.py
hermespy/modem/symbols.py
hermespy/modem/waveform.py
hermespy/modem/evaluators.py
hermespy/modem/bits_source.py
hermespy/modem/waveform_single_carrier.py
hermespy/modem/modem.py
hermespy/modem/waveform_chirp_fsk.py
hermespy/modem/__init__.py
hermespy/modem/waveform_correlation_synchronization.py
hermespy/modem/precoding/single_carrier.py
hermespy/modem/precoding/symbol_precoding.py
hermespy/modem/precoding/dft.py
hermespy/modem/precoding/space_time_block_coding.py
hermespy/modem/precoding/ratio_combining.py
hermespy/modem/precoding/__init__.py
hermespy/modem/waveforms/__init__.py
hermespy/modem/waveforms/orthogonal/ofdm.py
hermespy/modem/waveforms/orthogonal/waveform.py
hermespy/modem/waveforms/orthogonal/ocdm.py
hermespy/modem/waveforms/orthogonal/channel.py
hermespy/modem/waveforms/orthogonal/otfs.py
hermespy/modem/waveforms/orthogonal/__init__.py
hermespy/modem/frame_generator/scapy.py
hermespy/modem/frame_generator/frame_generator.py
hermespy/modem/frame_generator/__init__.py
hermespy/modem/tools/psk_qam_mapping.py
hermespy/modem/tools/__init__.py
hermespy/simulation/animation.py
hermespy/simulation/simulated_device.py
hermespy/simulation/scenario.py
hermespy/simulation/beamforming.py
hermespy/simulation/antennas.py
hermespy/simulation/__init__.py
hermespy/simulation/simulation.py
hermespy/simulation/drop.py
hermespy/simulation/coupling/impedance.py
hermespy/simulation/coupling/coupling.py
hermespy/simulation/coupling/perfect.py
hermespy/simulation/coupling/__init__.py
hermespy/simulation/modem/noise.py
hermespy/simulation/modem/channel_estimation.py
hermespy/simulation/modem/__init__.py
hermespy/simulation/rf_chain/rf_chain.py
hermespy/simulation/rf_chain/phase_noise.py
