Metadata-Version: 2.2
Name: hermespy
Version: 1.5.0
Summary: The Heterogeneous Radio Mobile Simulator
Keywords: simulation,link-level,communication,radar,channel,signal processing,MIMO,monte carlo
Author-Email: Jan Adler <jan.adler@barkhauseninstitut.org>
Maintainer-Email: Jan Adler <jan.adler@barkhauseninstitut.org>
License:                  Linking exception clause
Classifier: Programming Language :: Python :: 3.10
Classifier: Programming Language :: Python :: 3.11
Classifier: Programming Language :: Python :: 3.12
Classifier: License :: OSI Approved :: GNU Affero General Public License v3
Classifier: Operating System :: OS Independent
Classifier: Development Status :: 4 - Beta
Classifier: Natural Language :: English
Classifier: Topic :: Scientific/Engineering
Classifier: Intended Audience :: Science/Research
Project-URL: Documentation, https://hermespy.org/
Project-URL: Homepage, https://github.com/Barkhausen-Institut/hermespy.git
Project-URL: Issues, https://github.com/Barkhausen-Institut/hermespy/issues
Requires-Dist: numpy<=1.26.4
Requires-Dist: matplotlib>=3.10.0
Requires-Dist: h5py>=3.8.0
Requires-Dist: scipy>=1.14.1
Requires-Dist: pybind11>=2.10.4
Requires-Dist: ray>=2.40.0
Requires-Dist: sparse>=0.15.5
Requires-Dist: numba>=0.60.0
Requires-Dist: rich>=13.9.4
Provides-Extra: test
Requires-Dist: pytest>=7.4.2; extra == "test"
Requires-Dist: coverage>=7.5.1; extra == "test"
Requires-Dist: mypy>=1.13.0; extra == "test"
Requires-Dist: nbformat; extra == "test"
Requires-Dist: nbconvert; extra == "test"
Provides-Extra: quadriga
Requires-Dist: oct2py>=5.6.0; extra == "quadriga"
Provides-Extra: documentation
Requires-Dist: sphinx<8.2.0,>=8.0.0; extra == "documentation"
Requires-Dist: furo>=2024.8.6; extra == "documentation"
Requires-Dist: sphinx-autodoc-typehints>=3.0.1; extra == "documentation"
Requires-Dist: sphinxcontrib-apidoc>=0.5.0; extra == "documentation"
Requires-Dist: sphinxcontrib-mermaid>=1.0.0; extra == "documentation"
Requires-Dist: sphinxcontrib-bibtex>=2.6.3; extra == "documentation"
Requires-Dist: sphinx-tabs>=3.4.7; extra == "documentation"
Requires-Dist: sphinx-copybutton>=0.5.2; extra == "documentation"
Requires-Dist: sphinx-carousel>=1.2.0; extra == "documentation"
Requires-Dist: nbsphinx>=0.9.7; extra == "documentation"
Requires-Dist: ipywidgets==8.0.5; extra == "documentation"
Provides-Extra: uhd
Requires-Dist: usrp-uhd-client==1.7.3; extra == "uhd"
Provides-Extra: audio
Requires-Dist: sounddevice>=0.4.6; extra == "audio"
Provides-Extra: develop
Requires-Dist: pybind11>=2.13.6; extra == "develop"
Requires-Dist: scikit-build-core>=0.10.7; extra == "develop"
Requires-Dist: cmake>=3.31.2; extra == "develop"
Requires-Dist: wheel>=0.45.1; extra == "develop"
Requires-Dist: black>=24.10.0; extra == "develop"
Requires-Dist: flake8>=7.1.1; extra == "develop"
Requires-Dist: coverage>=7.6.9; extra == "develop"
Requires-Dist: mypy>=1.13.0; extra == "develop"
Provides-Extra: sionna
Requires-Dist: mitsuba<=3.5.2; extra == "sionna"
Requires-Dist: sionna==0.19.1; extra == "sionna"
Provides-Extra: scapy
Requires-Dist: scapy>=2.5.0; extra == "scapy"
